{
    "name": "PlayerInput",
    "inputActionAsset": {
        "instanceID": 24018
    },
    "controlSchemesList": [
        {
            "key": "Keyboard&Mouse",
            "value": true
        },
        {
            "key": "Gamepad",
            "value": true
        },
        {
            "key": "Touch",
            "value": false
        },
        {
            "key": "Joystick",
            "value": false
        },
        {
            "key": "XR",
            "value": false
        },
        {
            "key": "Keyboard & Mouse 2",
            "value": false
        },
        {
            "key": "Gamepad 2",
            "value": false
        }
    ]
}